pymfy/__init__.py
pymfy/api/__init__.py
pymfy/api/devices/__init__.py
pymfy/api/devices/base.py
pymfy/api/devices/blind.py
pymfy/api/devices/camera_protect.py
pymfy/api/devices/category.py
pymfy/api/devices/roller_shutter.py
pymfy/api/devices/thermostat.py
pymfy/api/model.py
pymfy/api/somfy_api.py
pymfy-0.10.1.dist-info/LICENSE
pymfy-0.10.1.dist-info/WHEEL
pymfy-0.10.1.dist-info/METADATA
pymfy-0.10.1.dist-info/RECORD
