Metadata-Version: 2.1
Name: pymfy
Version: 0.10.1
Summary: A Somfy Open API library
Home-page: https://github.com/tetienne/somfy-open-api
License: GPL-3.0-only
Author: ETIENNE Thibaut
Requires-Python: >=3.6.1,<4.0
Classifier: License :: OSI Approved :: GNU General Public License v3 (GPLv3)
Classifier: Programming Language :: Python :: 3
Classifier: Programming Language :: Python :: 3.7
Classifier: Programming Language :: Python :: 3.8
Requires-Dist: requests-oauthlib (>=1.3.0,<2.0.0)
Project-URL: Repository, https://github.com/tetienne/somfy-open-api
